exodar/__init__.py
exodar/func.py
exodar-0.0.5.dist-info/LICENSE
exodar-0.0.5.dist-info/METADATA
exodar-0.0.5.dist-info/WHEEL
exodar-0.0.5.dist-info/top_level.txt
exodar-0.0.5.dist-info/RECORD
