Metadata-Version: 2.1
Name: exodar
Version: 0.0.5
Summary: A test package
Author: vincent2303
Author-email: vincent.martin23@gmail.com
License: MIT
Classifier: License :: OSI Approved :: MIT License
Classifier: Programming Language :: Python :: 3.10
Classifier: Operating System :: OS Independent
Requires-Python: >=3.6
License-File: LICENSE
Requires-Dist: tqdm (>=4.62.2)
